README.rst
license.txt
setup.py
TSMasterAPI/TSAPI.py
TSMasterAPI/TSCallback.py
TSMasterAPI/TSDirver.py
TSMasterAPI/TSEnum.py
TSMasterAPI/TSFibex_parse.py
TSMasterAPI/TSMasterAPI.py
TSMasterAPI/TSStruct.py
TSMasterAPI/__init__.py
TSMasterAPI.egg-info/PKG-INFO
TSMasterAPI.egg-info/SOURCES.txt
TSMasterAPI.egg-info/dependency_links.txt
TSMasterAPI.egg-info/top_level.txt
TSMasterAPI/windows/bin/TSMaster.dll
TSMasterAPI/windows/bin64/TSMaster.dll
tsmasterapi.egg-info/PKG-INFO
tsmasterapi.egg-info/SOURCES.txt
tsmasterapi.egg-info/dependency_links.txt
tsmasterapi.egg-info/top_level.txt